{
    "id":  "tt0111873",
    "detail":  {
                   "id":  "tt0111873",
                   "type":  "tvSeries",
                   "primaryTitle":  "Æon Flux",
                   "primaryImage":  {
                                        "url":  "https://m.media-amazon.com/images/M/MV5BNTBiZWUwOTEtNDNlMy00Yjk3LTg5MTctNjgyZDYyZmNiYWY2XkEyXkFqcGc@._V1_.jpg",
                                        "width":  2405,
                                        "height":  3300
                                    },
                   "startYear":  1991,
                   "endYear":  1995,
                   "runtimeSeconds":  1800,
                   "genres":  [
                                  "Animation",
                                  "Action",
                                  "Adventure",
                                  "Sci-Fi",
                                  "Thriller"
                              ],
                   "rating":  {
                                  "aggregateRating":  7.8,
                                  "voteCount":  7966
                              },
                   "plot":  "There is a mysterious and immoral secret agent from the country of Monica. Her motives and background remain unexplained, as do those of her antagonist/lover, Trevor Goodchild.",
                   "directors":  [
                                     {
                                         "id":  "nm0161285",
                                         "displayName":  "Peter Chung",
                                         "alternativeNames":  [
                                                                  "P. Gun Chic Chung"
                                                              ],
                                         "primaryImage":  {
                                                              "url":  "https://m.media-amazon.com/images/M/MV5BMjI0MDMzMjE1Ml5BMl5BanBnXkFtZTcwNDgyNDY4NA@@._V1_.jpg",
                                                              "width":  852,
                                                              "height":  1024
                                                          },
                                         "primaryProfessions":  [
                                                                    "animation_department",
                                                                    "art_department",
                                                                    "writer"
                                                                ]
                                     },
                                     {
                                         "id":  "nm0048519",
                                         "displayName":  "Howard E. Baker",
                                         "alternativeNames":  [
                                                                  "Howard Baker"
                                                              ],
                                         "primaryProfessions":  [
                                                                    "animation_department",
                                                                    "art_department",
                                                                    "director"
                                                                ]
                                     },
                                     {
                                         "id":  "nm1656881",
                                         "displayName":  "J. Garett Sheldrew",
                                         "alternativeNames":  [
                                                                  "Garett Sheldrew",
                                                                  "Garrett Sheldrew",
                                                                  "J. Garrett Sheldrew",
                                                                  "James G. Sheldrew"
                                                              ],
                                         "primaryProfessions":  [
                                                                    "animation_department",
                                                                    "art_department",
                                                                    "director"
                                                                ]
                                     }
                                 ],
                   "writers":  [
                                   {
                                       "id":  "nm0161285",
                                       "displayName":  "Peter Chung",
                                       "alternativeNames":  [
                                                                "P. Gun Chic Chung"
                                                            ],
                                       "primaryImage":  {
                                                            "url":  "https://m.media-amazon.com/images/M/MV5BMjI0MDMzMjE1Ml5BMl5BanBnXkFtZTcwNDgyNDY4NA@@._V1_.jpg",
                                                            "width":  852,
                                                            "height":  1024
                                                        },
                                       "primaryProfessions":  [
                                                                  "animation_department",
                                                                  "art_department",
                                                                  "writer"
                                                              ]
                                   },
                                   {
                                       "id":  "nm0038871",
                                       "displayName":  "Japhet Asher",
                                       "primaryProfessions":  [
                                                                  "miscellaneous",
                                                                  "producer",
                                                                  "writer"
                                                              ]
                                   },
                                   {
                                       "id":  "nm0300756",
                                       "displayName":  "Peter Gaffney",
                                       "alternativeNames":  [
                                                                "Pete Gaffney"
                                                            ],
                                       "primaryProfessions":  [
                                                                  "miscellaneous",
                                                                  "producer",
                                                                  "writer"
                                                              ]
                                   }
                               ],
                   "stars":  [
                                 {
                                     "id":  "nm0497570",
                                     "displayName":  "John Rafter Lee",
                                     "alternativeNames":  [
                                                              "John Keefe",
                                                              "John R. Lee",
                                                              "John Lee"
                                                          ],
                                     "primaryImage":  {
                                                          "url":  "https://m.media-amazon.com/images/M/MV5BMTJkYTQzZDUtOGI1ZS00MTNhLTlhZjMtMmYzYjkwMWU0YzNmXkEyXkFqcGc@._V1_.jpg",
                                                          "width":  999,
                                                          "height":  879
                                                      },
                                     "primaryProfessions":  [
                                                                "actor",
                                                                "producer",
                                                                "writer"
                                                            ]
                                 },
                                 {
                                     "id":  "nm0688516",
                                     "displayName":  "Denise Poirier",
                                     "primaryProfessions":  [
                                                                "actress",
                                                                "miscellaneous"
                                                            ]
                                 },
                                 {
                                     "id":  "nm0218556",
                                     "displayName":  "Julia Fletcher",
                                     "alternativeNames":  [
                                                              "Julia De Mita",
                                                              "Julia DeMita",
                                                              "Julia Demita",
                                                              "Julia Dimita"
                                                          ],
                                     "primaryProfessions":  [
                                                                "actress",
                                                                "director",
                                                                "sound_department"
                                                            ]
                                 },
                                 {
                                     "id":  "nm0715078",
                                     "displayName":  "Max Redmond",
                                     "primaryProfessions":  [
                                                                "actor"
                                                            ]
                                 }
                             ],
                   "originCountries":  [
                                           {
                                               "code":  "US",
                                               "name":  "United States"
                                           }
                                       ],
                   "spokenLanguages":  [
                                           {
                                               "code":  "eng",
                                               "name":  "English"
                                           }
                                       ],
                   "interests":  [
                                     {
                                         "id":  "in0000001",
                                         "name":  "Action"
                                     },
                                     {
                                         "id":  "in0000012",
                                         "name":  "Adventure"
                                     },
                                     {
                                         "id":  "in0000025",
                                         "name":  "Adult Animation",
                                         "isSubgenre":  true
                                     },
                                     {
                                         "id":  "in0000026",
                                         "name":  "Animation"
                                     },
                                     {
                                         "id":  "in0000029",
                                         "name":  "Hand-Drawn Animation"
                                     },
                                     {
                                         "id":  "in0000159",
                                         "name":  "Cyberpunk",
                                         "isSubgenre":  true
                                     },
                                     {
                                         "id":  "in0000160",
                                         "name":  "Dystopian Sci-Fi",
                                         "isSubgenre":  true
                                     },
                                     {
                                         "id":  "in0000162",
                                         "name":  "Sci-Fi"
                                     },
                                     {
                                         "id":  "in0000184",
                                         "name":  "Spy",
                                         "isSubgenre":  true
                                     },
                                     {
                                         "id":  "in0000186",
                                         "name":  "Thriller"
                                     }
                                 ]
               },
    "seasons":  [
                    {
                        "season":  "1",
                        "episodeCount":  1
                    },
                    {
                        "season":  "2",
                        "episodeCount":  5
                    },
                    {
                        "season":  "3",
                        "episodeCount":  10
                    }
                ]
}
