{
    "id":  "tt0305011",
    "detail":  {
                   "id":  "tt0305011",
                   "type":  "tvSeries",
                   "primaryTitle":  "Clone High",
                   "primaryImage":  {
                                        "url":  "https://m.media-amazon.com/images/M/MV5BNGI1ZmY3OGQtOGRmMy00OWQ4LWJkMmEtMmE2ZTJmZTMyNzZkXkEyXkFqcGc@._V1_.jpg",
                                        "width":  1280,
                                        "height":  1920
                                    },
                   "startYear":  2002,
                   "endYear":  2003,
                   "runtimeSeconds":  1800,
                   "genres":  [
                                  "Animation",
                                  "Comedy",
                                  "Sci-Fi"
                              ],
                   "rating":  {
                                  "aggregateRating":  8.1,
                                  "voteCount":  9662
                              },
                   "plot":  "A high school is populated by the clones of well-known historical figures.",
                   "directors":  [
                                     {
                                         "id":  "nm0172881",
                                         "displayName":  "Ted Collyer",
                                         "primaryProfessions":  [
                                                                    "animation_department",
                                                                    "art_department",
                                                                    "assistant_director"
                                                                ]
                                     },
                                     {
                                         "id":  "nm0003696",
                                         "displayName":  "Harold Harris",
                                         "primaryProfessions":  [
                                                                    "director",
                                                                    "miscellaneous",
                                                                    "music_department"
                                                                ]
                                     },
                                     {
                                         "id":  "nm0520488",
                                         "displayName":  "Phil Lord",
                                         "alternativeNames":  [
                                                                  "Chris \u0026 Phil"
                                                              ],
                                         "primaryImage":  {
                                                              "url":  "https://m.media-amazon.com/images/M/MV5BOTI5NTUwMTAwOV5BMl5BanBnXkFtZTcwMDIxMDgzOQ@@._V1_.jpg",
                                                              "width":  1662,
                                                              "height":  2048
                                                          },
                                         "primaryProfessions":  [
                                                                    "actor",
                                                                    "producer",
                                                                    "writer"
                                                                ]
                                     }
                                 ],
                   "writers":  [
                                   {
                                       "id":  "nm0492639",
                                       "displayName":  "Bill Lawrence",
                                       "alternativeNames":  [
                                                                "Interrupting Bill"
                                                            ],
                                       "primaryImage":  {
                                                            "url":  "https://m.media-amazon.com/images/M/MV5BMTgwNjc4NzgyMV5BMl5BanBnXkFtZTcwMjg5MzA5Nw@@._V1_.jpg",
                                                            "width":  1153,
                                                            "height":  1997
                                                        },
                                       "primaryProfessions":  [
                                                                  "director",
                                                                  "producer",
                                                                  "writer"
                                                              ]
                                   },
                                   {
                                       "id":  "nm0520488",
                                       "displayName":  "Phil Lord",
                                       "alternativeNames":  [
                                                                "Chris \u0026 Phil"
                                                            ],
                                       "primaryImage":  {
                                                            "url":  "https://m.media-amazon.com/images/M/MV5BOTI5NTUwMTAwOV5BMl5BanBnXkFtZTcwMDIxMDgzOQ@@._V1_.jpg",
                                                            "width":  1662,
                                                            "height":  2048
                                                        },
                                       "primaryProfessions":  [
                                                                  "actor",
                                                                  "producer",
                                                                  "writer"
                                                              ]
                                   },
                                   {
                                       "id":  "nm0562582",
                                       "displayName":  "Mark Mayerson",
                                       "primaryProfessions":  [
                                                                  "animation_department",
                                                                  "director",
                                                                  "writer"
                                                              ]
                                   }
                               ],
                   "stars":  [
                                 {
                                     "id":  "nm0287182",
                                     "displayName":  "Will Forte",
                                     "alternativeNames":  [
                                                              "Orville Forte",
                                                              "William Forte"
                                                          ],
                                     "primaryImage":  {
                                                          "url":  "https://m.media-amazon.com/images/M/MV5BODE5ODkwNTg4Nl5BMl5BanBnXkFtZTcwODcwMTY1OQ@@._V1_.jpg",
                                                          "width":  1560,
                                                          "height":  2048
                                                      },
                                     "primaryProfessions":  [
                                                                "actor",
                                                                "producer",
                                                                "writer"
                                                            ]
                                 },
                                 {
                                     "id":  "nm0588096",
                                     "displayName":  "Christa Miller",
                                     "alternativeNames":  [
                                                              "Christa Miller Lawrence"
                                                          ],
                                     "primaryImage":  {
                                                          "url":  "https://m.media-amazon.com/images/M/MV5BMTQ4NDI4Nzc5N15BMl5BanBnXkFtZTYwNDIyNTcz._V1_.jpg",
                                                          "width":  267,
                                                          "height":  400
                                                      },
                                     "primaryProfessions":  [
                                                                "actress",
                                                                "location_management",
                                                                "music_department"
                                                            ]
                                 },
                                 {
                                     "id":  "nm0520488",
                                     "displayName":  "Phil Lord",
                                     "alternativeNames":  [
                                                              "Chris \u0026 Phil"
                                                          ],
                                     "primaryImage":  {
                                                          "url":  "https://m.media-amazon.com/images/M/MV5BOTI5NTUwMTAwOV5BMl5BanBnXkFtZTcwMDIxMDgzOQ@@._V1_.jpg",
                                                          "width":  1662,
                                                          "height":  2048
                                                      },
                                     "primaryProfessions":  [
                                                                "actor",
                                                                "producer",
                                                                "writer"
                                                            ]
                                 },
                                 {
                                     "id":  "nm0567912",
                                     "displayName":  "Michael McDonald",
                                     "alternativeNames":  [
                                                              "Michael James McDonald",
                                                              "Mike Mcdonald"
                                                          ],
                                     "primaryImage":  {
                                                          "url":  "https://m.media-amazon.com/images/M/MV5BYzBmYjI1ZDItZjhmOC00YWEzLTgxN2YtZmY5NzNmNWY0OTZhXkEyXkFqcGc@._V1_CR2149,0,2299,3449_.jpg",
                                                          "width":  2299,
                                                          "height":  3449
                                                      },
                                     "primaryProfessions":  [
                                                                "actor",
                                                                "director",
                                                                "producer"
                                                            ]
                                 }
                             ],
                   "originCountries":  [
                                           {
                                               "code":  "CA",
                                               "name":  "Canada"
                                           },
                                           {
                                               "code":  "US",
                                               "name":  "United States"
                                           }
                                       ],
                   "spokenLanguages":  [
                                           {
                                               "code":  "eng",
                                               "name":  "English"
                                           }
                                       ],
                   "interests":  [
                                     {
                                         "id":  "in0000026",
                                         "name":  "Animation"
                                     },
                                     {
                                         "id":  "in0000034",
                                         "name":  "Comedy"
                                     },
                                     {
                                         "id":  "in0000162",
                                         "name":  "Sci-Fi"
                                     }
                                 ]
               },
    "seasons":  [
                    {
                        "season":  "1",
                        "episodeCount":  13
                    }
                ]
}
