{
    "id":  "tt0955346",
    "detail":  {
                   "id":  "tt0955346",
                   "type":  "tvSeries",
                   "primaryTitle":  "Moonlight",
                   "primaryImage":  {
                                        "url":  "https://m.media-amazon.com/images/M/MV5BM2IzZDI1NzQtZWExMy00YmI2LTlmZGQtYzQyOGEyYjI2NDNmXkEyXkFqcGc@._V1_.jpg",
                                        "width":  1300,
                                        "height":  1950
                                    },
                   "startYear":  2007,
                   "endYear":  2008,
                   "runtimeSeconds":  3600,
                   "genres":  [
                                  "Crime",
                                  "Drama",
                                  "Fantasy",
                                  "Horror",
                                  "Romance",
                                  "Thriller"
                              ],
                   "rating":  {
                                  "aggregateRating":  7.6,
                                  "voteCount":  25959
                              },
                   "plot":  "An undead private investigator uses his unique talents to help the living.",
                   "directors":  [
                                     {
                                         "id":  "nm0870295",
                                         "displayName":  "Frederick E.O. Toye",
                                         "alternativeNames":  [
                                                                  "Fred E.O. Toye",
                                                                  "Frederick E. O. Toye",
                                                                  "Frederick O.E. Toye",
                                                                  "Frederick Toye",
                                                                  "Fredrick E.O. Toye",
                                                                  "Fred Toye"
                                                              ],
                                         "primaryImage":  {
                                                              "url":  "https://m.media-amazon.com/images/M/MV5BZGYyYmEzZTktMDkwZC00MTgyLWIzY2EtN2NkZTMyYjQ2MWJmXkEyXkFqcGc@._V1_.jpg",
                                                              "width":  4032,
                                                              "height":  3024
                                                          },
                                         "primaryProfessions":  [
                                                                    "director",
                                                                    "editor",
                                                                    "producer"
                                                                ]
                                     },
                                     {
                                         "id":  "nm1084723",
                                         "displayName":  "Chris Fisher",
                                         "primaryImage":  {
                                                              "url":  "https://m.media-amazon.com/images/M/MV5BZTdlNGI3YmItMjJkMi00ZjFlLWJmNjAtZWUzZjM2NTBjNWJmXkEyXkFqcGc@._V1_.jpg",
                                                              "width":  960,
                                                              "height":  637
                                                          },
                                         "primaryProfessions":  [
                                                                    "director",
                                                                    "producer",
                                                                    "writer"
                                                                ]
                                     },
                                     {
                                         "id":  "nm0389972",
                                         "displayName":  "Paul Holahan",
                                         "alternativeNames":  [
                                                                  "Paul Holohan"
                                                              ],
                                         "primaryImage":  {
                                                              "url":  "https://m.media-amazon.com/images/M/MV5BZDE2M2RhNmUtODNkMS00NzU0LWJiODEtNmQ2OGNlY2Q0NzdhXkEyXkFqcGc@._V1_.jpg",
                                                              "width":  445,
                                                              "height":  490
                                                          },
                                         "primaryProfessions":  [
                                                                    "cinematographer",
                                                                    "director",
                                                                    "producer"
                                                                ]
                                     }
                                 ],
                   "writers":  [
                                   {
                                       "id":  "nm0467193",
                                       "displayName":  "Ron Koslow",
                                       "primaryProfessions":  [
                                                                  "miscellaneous",
                                                                  "producer",
                                                                  "writer"
                                                              ]
                                   },
                                   {
                                       "id":  "nm0613271",
                                       "displayName":  "Trevor Munson",
                                       "primaryProfessions":  [
                                                                  "actor",
                                                                  "producer",
                                                                  "writer"
                                                              ]
                                   },
                                   {
                                       "id":  "nm0089369",
                                       "displayName":  "Jill E. Blotevogel",
                                       "alternativeNames":  [
                                                                "Jill Blotevogel",
                                                                "Jill Blotvogel"
                                                            ],
                                       "primaryProfessions":  [
                                                                  "miscellaneous",
                                                                  "producer",
                                                                  "writer"
                                                              ]
                                   }
                               ],
                   "stars":  [
                                 {
                                     "id":  "nm0617009",
                                     "displayName":  "Sophia Myles",
                                     "alternativeNames":  [
                                                              "Sophia Miles"
                                                          ],
                                     "primaryImage":  {
                                                          "url":  "https://m.media-amazon.com/images/M/MV5BMTgxMDI5MDY2Nl5BMl5BanBnXkFtZTcwNjA3ODYyMQ@@._V1_.jpg",
                                                          "width":  300,
                                                          "height":  420
                                                      },
                                     "primaryProfessions":  [
                                                                "actress"
                                                            ]
                                 },
                                 {
                                     "id":  "nm1533927",
                                     "displayName":  "Alex O\u0027Loughlin",
                                     "alternativeNames":  [
                                                              "Alex O\u0027Lachlan"
                                                          ],
                                     "primaryImage":  {
                                                          "url":  "https://m.media-amazon.com/images/M/MV5BNWJmOTUzMWEtMmU3MS00Yzk1LTk2MWQtNDFiMmVhYWFhZmQ1XkEyXkFqcGc@._V1_.jpg",
                                                          "width":  3024,
                                                          "height":  4032
                                                      },
                                     "primaryProfessions":  [
                                                                "actor",
                                                                "director",
                                                                "producer"
                                                            ]
                                 },
                                 {
                                     "id":  "nm0230655",
                                     "displayName":  "Jason Dohring",
                                     "primaryImage":  {
                                                          "url":  "https://m.media-amazon.com/images/M/MV5BMTQ0Mzg2MzQ5OF5BMl5BanBnXkFtZTYwNTg1NTM3._V1_.jpg",
                                                          "width":  375,
                                                          "height":  499
                                                      },
                                     "primaryProfessions":  [
                                                                "actor"
                                                            ]
                                 },
                                 {
                                     "id":  "nm0815370",
                                     "displayName":  "Shannyn Sossamon",
                                     "primaryImage":  {
                                                          "url":  "https://m.media-amazon.com/images/M/MV5BMDcxMjk2NTEtZDA2ZC00MWI4LWJmZmQtODQ3YjJlOTJmNGQwXkEyXkFqcGc@._V1_.jpg",
                                                          "width":  1000,
                                                          "height":  1506
                                                      },
                                     "primaryProfessions":  [
                                                                "actress",
                                                                "director",
                                                                "writer"
                                                            ]
                                 }
                             ],
                   "originCountries":  [
                                           {
                                               "code":  "US",
                                               "name":  "United States"
                                           }
                                       ],
                   "spokenLanguages":  [
                                           {
                                               "code":  "eng",
                                               "name":  "English"
                                           }
                                       ],
                   "interests":  [
                                     {
                                         "id":  "in0000052",
                                         "name":  "Crime"
                                     },
                                     {
                                         "id":  "in0000076",
                                         "name":  "Drama"
                                     },
                                     {
                                         "id":  "in0000098",
                                         "name":  "Fantasy"
                                     },
                                     {
                                         "id":  "in0000112",
                                         "name":  "Horror"
                                     },
                                     {
                                         "id":  "in0000119",
                                         "name":  "Vampire Horror",
                                         "isSubgenre":  true
                                     },
                                     {
                                         "id":  "in0000152",
                                         "name":  "Romance"
                                     },
                                     {
                                         "id":  "in0000186",
                                         "name":  "Thriller"
                                     }
                                 ]
               },
    "seasons":  [
                    {
                        "season":  "1",
                        "episodeCount":  16
                    },
                    {
                        "season":  "unknown",
                        "episodeCount":  1
                    }
                ]
}
