{
    "id":  "tt4643084",
    "detail":  {
                   "id":  "tt4643084",
                   "type":  "tvSeries",
                   "primaryTitle":  "Counterpart",
                   "primaryImage":  {
                                        "url":  "https://m.media-amazon.com/images/M/MV5BODg5NDU5NjM1NV5BMl5BanBnXkFtZTgwOTE0NjY1NjM@._V1_.jpg",
                                        "width":  768,
                                        "height":  1152
                                    },
                   "startYear":  2017,
                   "endYear":  2019,
                   "runtimeSeconds":  3600,
                   "genres":  [
                                  "Drama",
                                  "Sci-Fi",
                                  "Thriller"
                              ],
                   "rating":  {
                                  "aggregateRating":  8,
                                  "voteCount":  34610
                              },
                   "plot":  "A cog in a bureaucratic agency discovers his agency is guarding a crossing to a parallel dimension.",
                   "directors":  [
                                     {
                                         "id":  "nm0315298",
                                         "displayName":  "Jennifer Getzinger",
                                         "primaryImage":  {
                                                              "url":  "https://m.media-amazon.com/images/M/MV5BZjYwYmM3MDItZDVkNy00NzQwLWIyMDEtMTI1NzAxNjY2ZTU1XkEyXkFqcGc@._V1_.jpg",
                                                              "width":  3024,
                                                              "height":  4032
                                                          },
                                         "primaryProfessions":  [
                                                                    "director"
                                                                ]
                                     },
                                     {
                                         "id":  "nm0002399",
                                         "displayName":  "Alik Sakharov",
                                         "primaryImage":  {
                                                              "url":  "https://m.media-amazon.com/images/M/MV5BNGE0YWUzYjEtNTRlNy00YjUxLWJhMWItMGI4MTA2NDEyY2VkXkEyXkFqcGc@._V1_CR495,138,3032,4548_.jpg",
                                                              "width":  3032,
                                                              "height":  4548
                                                          },
                                         "primaryProfessions":  [
                                                                    "cinematographer",
                                                                    "director",
                                                                    "producer"
                                                                ]
                                     },
                                     {
                                         "id":  "nm0931724",
                                         "displayName":  "Stephen Williams",
                                         "primaryProfessions":  [
                                                                    "director",
                                                                    "producer",
                                                                    "writer"
                                                                ]
                                     }
                                 ],
                   "writers":  [
                                   {
                                       "id":  "nm1098479",
                                       "displayName":  "Justin Marks",
                                       "primaryImage":  {
                                                            "url":  "https://m.media-amazon.com/images/M/MV5BNjY4MjE3NzItNWI5Yy00MmI0LWI4ZmItOGZjZmU4ZWYxNjljXkEyXkFqcGc@._V1_CR103,0,929,1393_.jpg",
                                                            "width":  929,
                                                            "height":  1393
                                                        },
                                       "primaryProfessions":  [
                                                                  "miscellaneous",
                                                                  "producer",
                                                                  "writer"
                                                              ]
                                   },
                                   {
                                       "id":  "nm2144389",
                                       "displayName":  "Gianna Sobol",
                                       "primaryImage":  {
                                                            "url":  "https://m.media-amazon.com/images/M/MV5BMThhMTFiNDMtNjdmZi00ODJiLTg1ZmQtMDQ5MGY5N2UzYjU4XkEyXkFqcGc@._V1_.jpg",
                                                            "width":  2304,
                                                            "height":  1536
                                                        },
                                       "primaryProfessions":  [
                                                                  "miscellaneous",
                                                                  "producer",
                                                                  "writer"
                                                              ]
                                   },
                                   {
                                       "id":  "nm4033743",
                                       "displayName":  "Maegan Houang",
                                       "primaryImage":  {
                                                            "url":  "https://m.media-amazon.com/images/M/MV5BM2MzMzYzMTQtMTM1Ni00MmVkLTkxMzEtNzYwZTdiMWM5ZjljXkEyXkFqcGc@._V1_.jpg",
                                                            "width":  7265,
                                                            "height":  4846
                                                        },
                                       "primaryProfessions":  [
                                                                  "director",
                                                                  "miscellaneous",
                                                                  "writer"
                                                              ]
                                   }
                               ],
                   "stars":  [
                                 {
                                     "id":  "nm0799777",
                                     "displayName":  "J.K. Simmons",
                                     "alternativeNames":  [
                                                              "J. K. Simmons",
                                                              "JK Simmons",
                                                              "Jonathan Simmons"
                                                          ],
                                     "primaryImage":  {
                                                          "url":  "https://m.media-amazon.com/images/M/MV5BMzg2NTI5NzQ1MV5BMl5BanBnXkFtZTgwNjI1NDEwMDI@._V1_.jpg",
                                                          "width":  1679,
                                                          "height":  2048
                                                      },
                                     "primaryProfessions":  [
                                                                "actor",
                                                                "miscellaneous",
                                                                "soundtrack"
                                                            ]
                                 },
                                 {
                                     "id":  "nm0931404",
                                     "displayName":  "Olivia Williams",
                                     "primaryImage":  {
                                                          "url":  "https://m.media-amazon.com/images/M/MV5BMzIyOTEwMjYyNl5BMl5BanBnXkFtZTgwNTc3NDU0MjE@._V1_.jpg",
                                                          "width":  2000,
                                                          "height":  1464
                                                      },
                                     "primaryProfessions":  [
                                                                "actress",
                                                                "soundtrack"
                                                            ]
                                 },
                                 {
                                     "id":  "nm0516003",
                                     "displayName":  "Harry Lloyd",
                                     "primaryImage":  {
                                                          "url":  "https://m.media-amazon.com/images/M/MV5BMjE2OTkyOTkzMl5BMl5BanBnXkFtZTcwODYxMTUwOA@@._V1_.jpg",
                                                          "width":  1638,
                                                          "height":  2048
                                                      },
                                     "primaryProfessions":  [
                                                                "actor",
                                                                "producer",
                                                                "writer"
                                                            ]
                                 },
                                 {
                                     "id":  "nm2258164",
                                     "displayName":  "Nazanin Boniadi",
                                     "primaryImage":  {
                                                          "url":  "https://m.media-amazon.com/images/M/MV5BMTYyMDQ3NjI3MV5BMl5BanBnXkFtZTgwOTA5MTA5NjE@._V1_.jpg",
                                                          "width":  451,
                                                          "height":  590
                                                      },
                                     "primaryProfessions":  [
                                                                "actress",
                                                                "producer",
                                                                "writer"
                                                            ]
                                 }
                             ],
                   "originCountries":  [
                                           {
                                               "code":  "US",
                                               "name":  "United States"
                                           }
                                       ],
                   "spokenLanguages":  [
                                           {
                                               "code":  "eng",
                                               "name":  "English"
                                           },
                                           {
                                               "code":  "deu",
                                               "name":  "German"
                                           }
                                       ],
                   "interests":  [
                                     {
                                         "id":  "in0000076",
                                         "name":  "Drama"
                                     },
                                     {
                                         "id":  "in0000162",
                                         "name":  "Sci-Fi"
                                     },
                                     {
                                         "id":  "in0000186",
                                         "name":  "Thriller"
                                     }
                                 ]
               },
    "seasons":  [
                    {
                        "season":  "1",
                        "episodeCount":  10
                    },
                    {
                        "season":  "2",
                        "episodeCount":  10
                    }
                ]
}
