{
    "id":  "tt8336340",
    "detail":  {
                   "id":  "tt8336340",
                   "type":  "tvSeries",
                   "primaryTitle":  "Star Wars: Resistance",
                   "originalTitle":  "Star Wars Resistance",
                   "primaryImage":  {
                                        "url":  "https://m.media-amazon.com/images/M/MV5BMTkyMTc3NjAwNF5BMl5BanBnXkFtZTgwNTU1ODIyNjM@._V1_.jpg",
                                        "width":  1022,
                                        "height":  1500
                                    },
                   "startYear":  2018,
                   "endYear":  2020,
                   "runtimeSeconds":  1800,
                   "genres":  [
                                  "Animation",
                                  "Action",
                                  "Adventure",
                                  "Comedy",
                                  "Drama",
                                  "Family",
                                  "Fantasy",
                                  "Sci-Fi"
                              ],
                   "rating":  {
                                  "aggregateRating":  5.3,
                                  "voteCount":  9250
                              },
                   "plot":  "Kazuda Xiono, a young pilot for the Resistance, is tasked with a top secret mission to investigate the First Order, a growing threat in the galaxy.",
                   "directors":  [
                                     {
                                         "id":  "nm2198694",
                                         "displayName":  "Justin Ridge",
                                         "alternativeNames":  [
                                                                  "Bucket"
                                                              ],
                                         "primaryProfessions":  [
                                                                    "art_department",
                                                                    "director",
                                                                    "producer"
                                                                ]
                                     },
                                     {
                                         "id":  "nm2177723",
                                         "displayName":  "Steward Lee",
                                         "primaryProfessions":  [
                                                                    "animation_department",
                                                                    "art_department",
                                                                    "director"
                                                                ]
                                     },
                                     {
                                         "id":  "nm1656848",
                                         "displayName":  "Bosco Ng",
                                         "primaryProfessions":  [
                                                                    "animation_department",
                                                                    "art_department",
                                                                    "director"
                                                                ]
                                     }
                                 ],
                   "writers":  [
                                   {
                                       "id":  "nm2608366",
                                       "displayName":  "Carrie Beck",
                                       "primaryImage":  {
                                                            "url":  "https://m.media-amazon.com/images/M/MV5BOGI2Y2Q5ODQtMmYyNy00YzkyLWIzOWEtMGUyMGM1YWU4MmQ2XkEyXkFqcGc@._V1_.jpg",
                                                            "width":  416,
                                                            "height":  512
                                                        },
                                       "primaryProfessions":  [
                                                                  "miscellaneous",
                                                                  "producer",
                                                                  "writer"
                                                              ]
                                   },
                                   {
                                       "id":  "nm1396048",
                                       "displayName":  "Dave Filoni",
                                       "alternativeNames":  [
                                                                "C1-10P a.k.a. \u0027Chopper\u0027",
                                                                "Chopper",
                                                                "David Filoni"
                                                            ],
                                       "primaryImage":  {
                                                            "url":  "https://m.media-amazon.com/images/M/MV5BMTQzMzAxMTg3NV5BMl5BanBnXkFtZTcwNzEyNTQ4MQ@@._V1_.jpg",
                                                            "width":  267,
                                                            "height":  400
                                                        },
                                       "primaryProfessions":  [
                                                                  "director",
                                                                  "producer",
                                                                  "writer"
                                                              ]
                                   },
                                   {
                                       "id":  "nm1848009",
                                       "displayName":  "Kiri Hart",
                                       "primaryImage":  {
                                                            "url":  "https://m.media-amazon.com/images/M/MV5BMjA0Nzk4MDc0Nl5BMl5BanBnXkFtZTgwNDUyOTQ0OTE@._V1_.jpg",
                                                            "width":  1331,
                                                            "height":  2048
                                                        },
                                       "primaryProfessions":  [
                                                                  "miscellaneous",
                                                                  "producer",
                                                                  "writer"
                                                              ]
                                   }
                               ],
                   "stars":  [
                                 {
                                     "id":  "nm0569883",
                                     "displayName":  "Suzie McGrath",
                                     "primaryImage":  {
                                                          "url":  "https://m.media-amazon.com/images/M/MV5BMzI4NGIyZGUtYzc1NS00Y2M1LTkwMjktM2QxMjMwZDU1M2NmXkEyXkFqcGc@._V1_.jpg",
                                                          "width":  2048,
                                                          "height":  3072
                                                      },
                                     "primaryProfessions":  [
                                                                "actress",
                                                                "miscellaneous",
                                                                "stunts"
                                                            ]
                                 },
                                 {
                                     "id":  "nm1268478",
                                     "displayName":  "Christopher Sean",
                                     "alternativeNames":  [
                                                              "Christopher Sean Friel",
                                                              "Chris Friel"
                                                          ],
                                     "primaryImage":  {
                                                          "url":  "https://m.media-amazon.com/images/M/MV5BYWIyZTNlMWMtOTY4My00NDJkLTk0NTQtOWQ2OTAyNTdkMDY4XkEyXkFqcGc@._V1_.jpg",
                                                          "width":  600,
                                                          "height":  900
                                                      },
                                     "primaryProfessions":  [
                                                                "actor",
                                                                "stunts",
                                                                "writer"
                                                            ]
                                 },
                                 {
                                     "id":  "nm0493013",
                                     "displayName":  "Scott Lawrence",
                                     "primaryImage":  {
                                                          "url":  "https://m.media-amazon.com/images/M/MV5BMTc4NDgyMDMzNV5BMl5BanBnXkFtZTcwNDM2OTUzMQ@@._V1_.jpg",
                                                          "width":  450,
                                                          "height":  580
                                                      },
                                     "primaryProfessions":  [
                                                                "actor",
                                                                "miscellaneous",
                                                                "sound_department"
                                                            ]
                                 },
                                 {
                                     "id":  "nm3091777",
                                     "displayName":  "Josh Brener",
                                     "primaryImage":  {
                                                          "url":  "https://m.media-amazon.com/images/M/MV5BNDRlZjFjN2YtNGZlNi00NzY1LWJiMjEtNjQxMzZhN2QzYmE0XkEyXkFqcGc@._V1_.jpg",
                                                          "width":  900,
                                                          "height":  600
                                                      },
                                     "primaryProfessions":  [
                                                                "actor",
                                                                "producer",
                                                                "writer"
                                                            ]
                                 }
                             ],
                   "originCountries":  [
                                           {
                                               "code":  "US",
                                               "name":  "United States"
                                           }
                                       ],
                   "spokenLanguages":  [
                                           {
                                               "code":  "eng",
                                               "name":  "English"
                                           }
                                       ],
                   "interests":  [
                                     {
                                         "id":  "in0000001",
                                         "name":  "Action"
                                     },
                                     {
                                         "id":  "in0000008",
                                         "name":  "Superhero",
                                         "isSubgenre":  true
                                     },
                                     {
                                         "id":  "in0000012",
                                         "name":  "Adventure"
                                     },
                                     {
                                         "id":  "in0000026",
                                         "name":  "Animation"
                                     },
                                     {
                                         "id":  "in0000034",
                                         "name":  "Comedy"
                                     },
                                     {
                                         "id":  "in0000093",
                                         "name":  "Family"
                                     },
                                     {
                                         "id":  "in0000098",
                                         "name":  "Fantasy"
                                     },
                                     {
                                         "id":  "in0000162",
                                         "name":  "Sci-Fi"
                                     },
                                     {
                                         "id":  "in0000164",
                                         "name":  "Space Sci-Fi",
                                         "isSubgenre":  true
                                     }
                                 ]
               },
    "seasons":  [
                    {
                        "season":  "1",
                        "episodeCount":  20
                    },
                    {
                        "season":  "2",
                        "episodeCount":  18
                    },
                    {
                        "season":  "unknown",
                        "episodeCount":  12
                    }
                ]
}
